[
 {
   "ID": "3471DA17-401F-9633-BF81-4CADA6FD5C79",
   "Name": "Kyra Lester",
   "Description": "Curabitur dictum. Phasellus in",
   "Date": "2017-07-23T04:24:49-07:00",
   "Amount": 345.54
 },
 {
   "ID": "9F5C9912-936A-FB85-1EDB-9DA87BE7FF1E",
   "Name": "Buckminster Alvarado",
   "Description": "dui, in sodales elit erat vitae risus. Duis a mi",
   "Date": "2018-11-08T05:44:15-08:00",
   "Amount": 677.08
 },
 {
   "ID": "B743AC82-3613-13A2-2E42-E0C1F5CBF8A6",
   "Name": "Athena Smith",
   "Description": "massa lobortis ultrices. Vivamus rhoncus.",
   "Date": "2018-11-11T06:19:57-08:00",
   "Amount": 73.67
 },
 {
   "ID": "74749D4F-A43F-34E8-A687-D54924B17251",
   "Name": "Cameron Thompson",
   "Description": "dolor. Fusce mi lorem, vehicula et, rutrum eu,",
   "Date": "2019-09-30T06:56:15-07:00",
   "Amount": 807.6
 },
 {
   "ID": "DB983FEF-AF70-7D2E-86BA-0C2AE749E729",
   "Name": "Dawn Alford",
   "Description": "Pellentesque ut ipsum",
   "Date": "2019-03-06T13:24:31-08:00",
   "Amount": 820.96
 },
 {
   "ID": "8E6F38E1-5DC7-5030-4513-8FBB237EF5DB",
   "Name": "Barclay Sears",
   "Description": "sit amet ultricies sem magna",
   "Date": "2019-10-28T04:57:29-07:00",
   "Amount": 116.36
 },
 {
   "ID": "4891AA6C-02DF-A955-951C-9CEEC6D69387",
   "Name": "James Melton",
   "Description": "non leo. Vivamus nibh dolor, nonummy ac, feugiat non, lobortis",
   "Date": "2019-03-13T09:43:05-07:00",
   "Amount": 956.72
 },
 {
   "ID": "7BF06B3D-5DF2-9EEA-9E32-1BB284D0ABB9",
   "Name": "Medge Powell",
   "Description": "elit sed",
   "Date": "2018-01-19T20:33:11-08:00",
   "Amount": 726.37
 },
 {
   "ID": "5DEB3210-1591-B14D-1D51-389F84099E84",
   "Name": "Lucas Ray",
   "Description": "morbi tristique senectus",
   "Date": "2017-06-19T14:05:17-07:00",
   "Amount": -439.33
 },
 {
   "ID": "96C6E014-B8DE-7ED0-B0D2-2D1577D2427C",
   "Name": "Wang Stevens",
   "Description": "ipsum",
   "Date": "2018-02-12T09:36:23-08:00",
   "Amount": 638.14
 },
 {
   "ID": "E267C0EE-D5EA-8F7A-96AB-E78817E6FFFA",
   "Name": "Dalton Carey",
   "Description": "lectus justo eu arcu. Morbi sit amet massa. Quisque",
   "Date": "2018-07-31T15:51:48-07:00",
   "Amount": 602.37
 },
 {
   "ID": "EF0C48A4-06A3-0437-F9A5-426B1BB00A5F",
   "Name": "Jackson Noel",
   "Description": "dui,",
   "Date": "2019-03-16T03:52:39-07:00",
   "Amount": -319.59
 },
 {
   "ID": "412A0487-22C3-4183-3E2F-AF900725DD38",
   "Name": "Ariana Kennedy",
   "Description": "eleifend nec, malesuada ut, sem. Nulla interdum. Curabitur dictum.",
   "Date": "2018-09-07T09:06:19-07:00",
   "Amount": 618.05
 },
 {
   "ID": "BF6A5A4C-4281-84EF-CAAA-FECA9BFD1F9F",
   "Name": "Bevis Mcfadden",
   "Description": "sagittis",
   "Date": "2019-01-22T10:28:19-08:00",
   "Amount": 400.65
 },
 {
   "ID": "398D3DD0-647D-168A-756D-2B48FEC07D7F",
   "Name": "Kasimir Byrd",
   "Description": "ridiculus mus. Donec dignissim",
   "Date": "2017-09-30T17:57:57-07:00",
   "Amount": 159.61
 },
 {
   "ID": "1BDF7A90-717E-56EE-355B-14D344F86878",
   "Name": "Ava Sargent",
   "Description": "Cum sociis natoque",
   "Date": "2017-08-20T20:20:34-07:00",
   "Amount": 462.91
 },
 {
   "ID": "F0E82B90-EE28-1D9E-7722-EF276A54C415",
   "Name": "Gray Keith",
   "Description": "interdum. Curabitur dictum. Phasellus in felis. Nulla tempor",
   "Date": "2018-12-26T09:43:45-08:00",
   "Amount": -792.3
 },
 {
   "ID": "2EFFF684-5F6D-F707-25DC-E2222B2151C3",
   "Name": "Neil Clemons",
   "Description": "molestie. Sed id",
   "Date": "2019-06-14T02:43:16-07:00",
   "Amount": 337.64
 },
 {
   "ID": "18C7AEC2-054E-3746-1E9D-B81DC3B270F2",
   "Name": "Tad Knapp",
   "Description": "Donec egestas. Duis ac arcu. Nunc mauris. Morbi",
   "Date": "2018-02-23T23:41:07-08:00",
   "Amount": 932.52
 },
 {
   "ID": "02EE993A-5D8E-7448-0217-6874B4CAEE80",
   "Name": "April Fields",
   "Description": "urna convallis erat, eget tincidunt dui augue",
   "Date": "2019-03-04T20:58:53-08:00",
   "Amount": 865.94
 },
 {
   "ID": "894CC0E6-8439-B85B-DC23-6D29E7900A93",
   "Name": "Lester Mayer",
   "Description": "erat. Sed nunc est, mollis non,",
   "Date": "2019-05-20T11:56:46-07:00",
   "Amount": 335.28
 },
 {
   "ID": "B213B4AF-0082-7B59-029A-5557AF11E770",
   "Name": "Harriet Castillo",
   "Description": "orci. Ut semper pretium neque.",
   "Date": "2019-10-25T12:19:40-07:00",
   "Amount": 283.23
 },
 {
   "ID": "34FC88F1-BA66-9429-A35C-942CB4E5EB47",
   "Name": "Aubrey Sheppard",
   "Description": "tellus sem mollis dui, in sodales elit erat vitae risus.",
   "Date": "2018-07-14T05:07:40-07:00",
   "Amount": 689.31
 },
 {
   "ID": "0E527195-AAED-B7FC-7E4F-D2DFE24C3103",
   "Name": "Sebastian Baldwin",
   "Description": "rhoncus. Donec est. Nunc",
   "Date": "2018-06-12T00:32:55-07:00",
   "Amount": 172.09
 },
 {
   "ID": "25E590E4-6879-D85F-0364-CF00F15A344F",
   "Name": "Emerald Rice",
   "Description": "lobortis risus. In mi pede,",
   "Date": "2017-12-19T11:59:39-08:00",
   "Amount": 564.16
 },
 {
   "ID": "7BD4F1C3-6377-0FF3-F337-7A227A8896DA",
   "Name": "Britanni Beck",
   "Description": "ac",
   "Date": "2018-04-04T18:42:22-07:00",
   "Amount": 722.49
 },
 {
   "ID": "A7AAEA8B-94C2-8E31-70B0-49E97E32C950",
   "Name": "Quon Herring",
   "Description": "lobortis augue scelerisque mollis. Phasellus libero mauris,",
   "Date": "2018-06-21T17:18:42-07:00",
   "Amount": 847.41
 },
 {
   "ID": "6BB82E69-B2AF-22A3-FE97-FD4E3C69FEE1",
   "Name": "Hedley Parks",
   "Description": "adipiscing non,",
   "Date": "2019-03-07T23:56:56-08:00",
   "Amount": -128.23
 },
 {
   "ID": "7F91FA55-C2DB-8706-F9BD-E6F280D58FB6",
   "Name": "Randall Walters",
   "Description": "mattis velit justo nec",
   "Date": "2018-06-13T20:07:59-07:00",
   "Amount": 216.91
 },
 {
   "ID": "C56F9D71-865C-326B-9687-1E79A67B0492",
   "Name": "Trevor Reilly",
   "Description": "placerat eget, venenatis a, magna. Lorem ipsum dolor",
   "Date": "2019-08-16T08:24:47-07:00",
   "Amount": 165.99
 },
 {
   "ID": "5A52721F-8F20-DAE1-3FB5-ACA3DA97F9C4",
   "Name": "Steel Delgado",
   "Description": "ligula tortor, dictum eu, placerat eget, venenatis a, magna. Lorem",
   "Date": "2019-01-21T05:04:05-08:00",
   "Amount": 214.03
 },
 {
   "ID": "D24EC25D-5A33-B02E-626F-D2D51D5BA170",
   "Name": "Knox Mendoza",
   "Description": "diam vel arcu. Curabitur ut",
   "Date": "2019-09-01T22:29:06-07:00",
   "Amount": 287.03
 },
 {
   "ID": "12FDCA70-FB3E-8179-C467-4A99D80B01DD",
   "Name": "Mark Benjamin",
   "Description": "nulla ante, iaculis nec, eleifend non, dapibus rutrum, justo.",
   "Date": "2017-08-02T07:48:03-07:00",
   "Amount": 521.11
 },
 {
   "ID": "D0191AF1-FE1F-BD92-6538-9163057EB98E",
   "Name": "Louis Clemons",
   "Description": "est,",
   "Date": "2019-06-14T16:53:44-07:00",
   "Amount": -423.98
 },
 {
   "ID": "65876E9B-C0E6-874B-6E81-A23E68F66764",
   "Name": "Virginia Aguilar",
   "Description": "ante lectus convallis est,",
   "Date": "2017-08-29T12:49:59-07:00",
   "Amount": 869.45
 },
 {
   "ID": "04077D79-8715-AF29-B092-F6B269EEEFF3",
   "Name": "Axel Fuller",
   "Description": "dapibus ligula. Aliquam erat",
   "Date": "2019-01-31T15:26:13-08:00",
   "Amount": 294.95
 },
 {
   "ID": "A9D9903A-B44B-59D5-EA86-922324EC4803",
   "Name": "Palmer Medina",
   "Description": "leo, in lobortis tellus justo",
   "Date": "2019-04-15T20:56:08-07:00",
   "Amount": 530.27
 },
 {
   "ID": "2739A76C-C48D-FC4D-A1AA-4957599ECD3F",
   "Name": "Isabelle Fitzgerald",
   "Description": "egestas",
   "Date": "2019-02-18T05:45:45-08:00",
   "Amount": 377.87
 },
 {
   "ID": "53E78273-A342-3708-7FEF-41F3B5921DAD",
   "Name": "Dante Morris",
   "Description": "in, tempus eu, ligula. Aenean euismod mauris eu",
   "Date": "2017-06-16T07:47:35-07:00",
   "Amount": 11.47
 },
 {
   "ID": "5BA3EA0F-78DF-5D46-9185-27B2ADE7B56A",
   "Name": "Rajah Blake",
   "Description": "feugiat. Lorem",
   "Date": "2018-11-15T18:13:06-08:00",
   "Amount": 186.33
 },
 {
   "ID": "53337A98-709D-2BF9-4BA7-761C531E7CA6",
   "Name": "Tatyana Hester",
   "Description": "nec mauris blandit",
   "Date": "2018-05-07T23:18:26-07:00",
   "Amount": 33.9
 },
 {
   "ID": "A09A9C02-F51C-9CC6-4E06-EB06C47C8EE0",
   "Name": "Yael Horn",
   "Description": "metus. Aliquam erat volutpat. Nulla facilisis. Suspendisse",
   "Date": "2018-04-05T03:39:20-07:00",
   "Amount": 251.97
 },
 {
   "ID": "1936BE52-F6BC-A6BE-3C6E-500AF64C1B2D",
   "Name": "Christopher May",
   "Description": "Cum sociis natoque penatibus et magnis dis parturient",
   "Date": "2017-07-12T19:50:08-07:00",
   "Amount": -747.92
 },
 {
   "ID": "17528C9F-773F-1651-55AE-848FDAABE446",
   "Name": "Bertha Strong",
   "Description": "hendrerit.",
   "Date": "2018-05-22T00:16:48-07:00",
   "Amount": 420.64
 },
 {
   "ID": "61CBD2A7-C3C7-87C7-8072-C1E86220A07A",
   "Name": "Darryl Rosario",
   "Description": "vitae, sodales at, velit. Pellentesque ultricies dignissim lacus. Aliquam rutrum",
   "Date": "2018-06-24T20:25:09-07:00",
   "Amount": 44.99
 },
 {
   "ID": "8668B8F0-7622-1ECC-DAC8-47751BFADA7D",
   "Name": "Joan Bean",
   "Description": "risus. Nulla eget metus eu erat",
   "Date": "2017-05-04T10:11:50-07:00",
   "Amount": 313.18
 },
 {
   "ID": "67C61ACD-F36C-9E5C-F5C9-1C48C3644F8C",
   "Name": "Hedda Rowe",
   "Description": "egestas nunc sed libero. Proin sed turpis nec",
   "Date": "2019-06-30T04:29:56-07:00",
   "Amount": 412.51
 },
 {
   "ID": "28CB7BA0-4EE5-15A3-C781-1D4E57B01F56",
   "Name": "Davis Warner",
   "Description": "dolor. Nulla semper tellus id nunc",
   "Date": "2017-10-10T11:22:10-07:00",
   "Amount": 175.14
 },
 {
   "ID": "E624450C-EACE-C049-A094-AEA22E62DF2B",
   "Name": "Tasha Rodriquez",
   "Description": "ac libero nec ligula consectetuer rhoncus. Nullam velit dui, semper",
   "Date": "2018-10-01T08:03:47-07:00",
   "Amount": 285.6
 },
 {
   "ID": "D51E6B1C-EFD0-B602-DCA8-2F2ABC49693E",
   "Name": "Kiona Stephens",
   "Description": "purus sapien,",
   "Date": "2018-04-01T16:54:28-07:00",
   "Amount": 271.16
 },
 {
   "ID": "F395FFC4-E8B9-9C51-A7B7-012A8A1D0FD7",
   "Name": "Connor Harding",
   "Description": "In",
   "Date": "2017-12-30T00:57:37-08:00",
   "Amount": 814.88
 },
 {
   "ID": "881F6357-5CAA-B0FF-A711-037E8D2384D4",
   "Name": "Ferris Gallagher",
   "Description": "nec tempus scelerisque, lorem",
   "Date": "2018-03-03T00:27:51-08:00",
   "Amount": 156.74
 },
 {
   "ID": "011FF0B3-EEE2-202B-66AE-D64933319F3F",
   "Name": "Aurelia Pearson",
   "Description": "et magnis dis parturient montes, nascetur ridiculus mus. Donec",
   "Date": "2018-11-15T19:15:30-08:00",
   "Amount": -637.04
 },
 {
   "ID": "9EE856BF-03AC-8314-DB99-4846DBAC6744",
   "Name": "Patience Schultz",
   "Description": "lobortis quam a felis",
   "Date": "2018-04-24T07:38:38-07:00",
   "Amount": 426.17
 },
 {
   "ID": "663F9D4F-C419-F371-B2B4-0BFCABF13C83",
   "Name": "Vernon Fischer",
   "Description": "eu sem. Pellentesque ut",
   "Date": "2018-01-28T08:58:47-08:00",
   "Amount": 953.61
 },
 {
   "ID": "2CA45112-1C4A-593D-3C8F-2D0F952B0DCF",
   "Name": "Beck Frank",
   "Description": "luctus lobortis. Class aptent taciti",
   "Date": "2018-12-02T07:56:07-08:00",
   "Amount": 451.62
 },
 {
   "ID": "84E8A8EE-5A8F-44CA-F8A7-97A1BD972B16",
   "Name": "Kadeem Buchanan",
   "Description": "Donec porttitor tellus non magna. Nam",
   "Date": "2019-09-13T02:27:42-07:00",
   "Amount": -333.55
 },
 {
   "ID": "09AC2F26-025D-536F-F123-F7A1DF9CC749",
   "Name": "Ezekiel Carey",
   "Description": "eu turpis. Nulla aliquet.",
   "Date": "2019-08-25T00:47:31-07:00",
   "Amount": 451.17
 },
 {
   "ID": "2BA04E0D-551F-BDE6-E6C9-E890D0DE1C9D",
   "Name": "Florence Mcmillan",
   "Description": "Quisque purus sapien, gravida",
   "Date": "2018-01-27T10:53:39-08:00",
   "Amount": 953.54
 },
 {
   "ID": "B4630949-F331-B3B1-86A3-01ADD40190FA",
   "Name": "Wendy Parrish",
   "Description": "condimentum",
   "Date": "2018-10-24T12:02:31-07:00",
   "Amount": -546.89
 },
 {
   "ID": "8F982E66-CA23-AAA8-B5E9-A83B7C383995",
   "Name": "Allistair Cantrell",
   "Description": "enim nec tempus",
   "Date": "2019-05-31T12:33:10-07:00",
   "Amount": 454.62
 },
 {
   "ID": "D41188E2-CE05-7B96-F6D3-0F33D29F7181",
   "Name": "Lael Ingram",
   "Description": "Cras vehicula aliquet libero. Integer in magna. Phasellus dolor",
   "Date": "2017-05-09T13:11:55-07:00",
   "Amount": 320.69
 },
 {
   "ID": "34217945-A59A-1E46-3A78-CEF67B95F9F6",
   "Name": "Paul Kirkland",
   "Description": "aliquet lobortis, nisi nibh",
   "Date": "2019-02-14T00:29:32-08:00",
   "Amount": 135.2
 },
 {
   "ID": "E20E7C23-D137-2EFE-2EC5-E778DB1AB8C8",
   "Name": "Inez Ruiz",
   "Description": "nisl arcu iaculis enim, sit amet ornare",
   "Date": "2019-01-23T09:23:52-08:00",
   "Amount": -636.08
 },
 {
   "ID": "9E50D3EF-F272-FB28-67E4-FDE148B9080E",
   "Name": "Tiger Larson",
   "Description": "Nulla semper tellus id nunc",
   "Date": "2019-07-20T14:51:13-07:00",
   "Amount": 564.5
 },
 {
   "ID": "F9D22B48-C3B1-6D34-8518-F2144CBC567C",
   "Name": "Lev Hardy",
   "Description": "elementum, lorem ut aliquam iaculis, lacus pede sagittis augue,",
   "Date": "2019-01-24T13:16:30-08:00",
   "Amount": 292.09
 },
 {
   "ID": "B1B03A2F-1893-B083-6234-912C40D46DA3",
   "Name": "Cally Mcguire",
   "Description": "in consequat enim diam vel arcu. Curabitur ut odio vel",
   "Date": "2019-03-25T10:53:00-07:00",
   "Amount": 123.53
 },
 {
   "ID": "DCDDAD5C-5F24-432C-EACD-41D47C96DC4E",
   "Name": "India Gregory",
   "Description": "magna tellus",
   "Date": "2017-07-17T01:31:50-07:00",
   "Amount": 343.79
 },
 {
   "ID": "CFF12D1A-296C-B89E-D39E-A7F8537EC5D0",
   "Name": "Hedy Vance",
   "Description": "et, euismod et,",
   "Date": "2018-03-21T00:30:14-07:00",
   "Amount": 333.7
 },
 {
   "ID": "63443E6A-8979-CB52-C700-9FED4A37EBD1",
   "Name": "Keane Fisher",
   "Description": "pellentesque",
   "Date": "2019-07-10T23:05:49-07:00",
   "Amount": -476.18
 },
 {
   "ID": "10383256-CDAB-652B-3CA4-1385B63C567D",
   "Name": "Madaline Roach",
   "Description": "sit amet nulla. Donec non justo. Proin",
   "Date": "2018-09-27T13:32:37-07:00",
   "Amount": 756.1
 },
 {
   "ID": "23E2DC98-B413-9D2D-80C2-4657E7480E7F",
   "Name": "Jamalia Nixon",
   "Description": "id sapien.",
   "Date": "2019-08-09T04:16:20-07:00",
   "Amount": 302.84
 },
 {
   "ID": "F8A74355-9BD6-ACCB-E739-A202DAEAF73A",
   "Name": "Byron Morse",
   "Description": "ultrices iaculis",
   "Date": "2018-10-05T12:58:32-07:00",
   "Amount": 356.93
 },
 {
   "ID": "BFD07A65-A4F4-86B4-8199-26B2BBE3372E",
   "Name": "Kirby Hendricks",
   "Description": "pede. Cras vulputate velit eu sem. Pellentesque",
   "Date": "2018-11-19T13:14:37-08:00",
   "Amount": 97.47
 },
 {
   "ID": "99F1070B-5CB8-EA8F-3C84-5C051FF45908",
   "Name": "Jada Ferrell",
   "Description": "risus. Duis a mi fringilla mi lacinia",
   "Date": "2019-05-02T03:47:48-07:00",
   "Amount": 327.01
 },
 {
   "ID": "06F29E14-D855-6730-C5A6-F997453B2649",
   "Name": "Aimee Davidson",
   "Description": "sodales nisi magna sed dui. Fusce aliquam,",
   "Date": "2019-08-01T05:42:16-07:00",
   "Amount": -223.23
 },
 {
   "ID": "FFC14F4E-8350-CDE3-04F4-3502816C5273",
   "Name": "Salvador Robinson",
   "Description": "condimentum. Donec",
   "Date": "2018-07-12T12:04:16-07:00",
   "Amount": 153.83
 },
 {
   "ID": "2FF3CD32-5E72-9AB5-8032-ED611EE5C41F",
   "Name": "Brooke May",
   "Description": "nibh. Donec est mauris, rhoncus",
   "Date": "2018-07-15T06:03:48-07:00",
   "Amount": 802.19
 },
 {
   "ID": "28D2A950-11CA-B10F-F1FE-BC3A52F4AE35",
   "Name": "Beverly Grimes",
   "Description": "sollicitudin a, malesuada",
   "Date": "2019-08-07T17:08:36-07:00",
   "Amount": 126.25
 },
 {
   "ID": "38879577-44AB-E880-61A1-2059DBF7CA5B",
   "Name": "Iona Newton",
   "Description": "sed orci lobortis augue",
   "Date": "2017-06-15T14:19:32-07:00",
   "Amount": 403.7
 },
 {
   "ID": "1249974D-5384-C90A-0F85-CC24B1294F23",
   "Name": "Brandon Hoover",
   "Description": "malesuada id, erat.",
   "Date": "2018-11-09T21:07:01-08:00",
   "Amount": 967.89
 },
 {
   "ID": "43203BC8-351A-6D27-179C-4EE8B2CDCF5D",
   "Name": "Ashely Johnston",
   "Description": "commodo",
   "Date": "2017-06-16T15:38:40-07:00",
   "Amount": 90.81
 },
 {
   "ID": "083DE117-B408-DB7D-B5DC-36061B452658",
   "Name": "Nichole Guzman",
   "Description": "arcu. Curabitur ut odio vel est",
   "Date": "2018-02-16T03:12:10-08:00",
   "Amount": 465.53
 },
 {
   "ID": "F89BD5F5-1B98-B605-20BB-8A71329FC6C3",
   "Name": "Nyssa Daniel",
   "Description": "euismod urna. Nullam lobortis quam a felis ullamcorper viverra.",
   "Date": "2018-02-27T13:55:13-08:00",
   "Amount": 496.15
 },
 {
   "ID": "96A4F6CE-2354-629B-A82E-9E5AE92CEF55",
   "Name": "Cameron Walters",
   "Description": "sagittis semper. Nam tempor diam dictum sapien. Aenean",
   "Date": "2017-09-10T06:57:41-07:00",
   "Amount": 430.33
 },
 {
   "ID": "4886868B-E445-B250-4A3E-E65E6E8B73D0",
   "Name": "Malik Woodard",
   "Description": "nisi. Aenean eget metus. In nec orci. Donec nibh.",
   "Date": "2017-11-01T13:41:06-07:00",
   "Amount": -105.48
 },
 {
   "ID": "6C2B0D2F-766C-78CC-7159-2AD84D8FABEC",
   "Name": "Cora Kinney",
   "Description": "molestie. Sed id risus quis diam luctus lobortis. Class aptent",
   "Date": "2019-02-24T23:29:42-08:00",
   "Amount": 581.44
 },
 {
   "ID": "5E954E47-EE6D-47AA-E227-0A5D5526B969",
   "Name": "Patricia Valentine",
   "Description": "est ac",
   "Date": "2018-10-11T08:44:36-07:00",
   "Amount": 20.19
 },
 {
   "ID": "C35EBB87-DA3F-4649-54B9-0C306BA7EBDB",
   "Name": "Azalia Harrell",
   "Description": "Mauris magna. Duis dignissim tempor arcu. Vestibulum ut",
   "Date": "2019-09-02T20:20:37-07:00",
   "Amount": 867.99
 },
 {
   "ID": "C3200B83-9A66-C157-AB92-EED9FD254DB6",
   "Name": "Tarik Herman",
   "Description": "ante dictum mi, ac mattis",
   "Date": "2018-12-31T19:29:31-08:00",
   "Amount": 404.63
 },
 {
   "ID": "A10A2E7C-4A0D-1277-B9CF-CDE072371907",
   "Name": "Signe Moody",
   "Description": "mauris eu elit. Nulla facilisi. Sed",
   "Date": "2017-09-15T18:33:36-07:00",
   "Amount": 330.95
 },
 {
   "ID": "E04E74CE-8D7A-B9F2-1678-4BB2B5694950",
   "Name": "Cameron Tate",
   "Description": "eu neque pellentesque massa lobortis ultrices. Vivamus rhoncus. Donec est.",
   "Date": "2019-07-29T01:18:22-07:00",
   "Amount": 593.45
 },
 {
   "ID": "BD46E57D-2F83-B2F7-678F-84B4B33E2A60",
   "Name": "Omar Tillman",
   "Description": "vulputate velit eu sem.",
   "Date": "2017-11-02T10:50:11-07:00",
   "Amount": -596.23
 },
 {
   "ID": "76277018-6332-4BF2-E4A5-6FB2C5B7541C",
   "Name": "Leroy Parsons",
   "Description": "dignissim pharetra. Nam ac nulla. In tincidunt congue turpis.",
   "Date": "2018-01-10T11:33:14-08:00",
   "Amount": 566.14
 },
 {
   "ID": "96F608BA-C16A-ADFC-AE65-951CEECE80EE",
   "Name": "Iliana Dotson",
   "Description": "sodales at,",
   "Date": "2018-05-06T19:52:47-07:00",
   "Amount": -180.4
 },
 {
   "ID": "3941BD2C-79E7-AAC8-3DFC-9FCFBCBC6AB2",
   "Name": "Galena Chavez",
   "Description": "Quisque tincidunt pede ac",
   "Date": "2018-06-30T12:41:49-07:00",
   "Amount": 682.43
 },
 {
   "ID": "ED438518-1818-EE87-D8D9-A2D1B639E030",
   "Name": "Laurel Chen",
   "Description": "Nunc sed orci lobortis",
   "Date": "2017-09-01T18:45:23-07:00",
   "Amount": 381.91
 },
 {
   "ID": "81BC7A46-04B8-A051-B5DB-F9270E9BCD4E",
   "Name": "Dillon Mccoy",
   "Description": "est ac mattis semper, dui lectus rutrum urna,",
   "Date": "2018-03-21T20:03:56-07:00",
   "Amount": 597.5
 },
 {
   "ID": "C0DC95CC-E432-998F-05EB-8BC8D37F0FCF",
   "Name": "Eve Bryan",
   "Description": "id risus quis diam luctus lobortis. Class aptent taciti",
   "Date": "2018-12-07T07:08:35-08:00",
   "Amount": 594.32
 },
 {
   "ID": "17019E51-E9B9-2E41-ECA4-3691F74BABA1",
   "Name": "Denise Walsh",
   "Description": "Mauris",
   "Date": "2017-07-18T08:53:37-07:00",
   "Amount": 946.99
 }
]